merlinth/__init__.py
merlinth/complex.py
merlinth/math.py
merlinth/utils.py
merlinth/layers/__init__.py
merlinth/layers/complex_act.py
merlinth/layers/complex_avgpool.py
merlinth/layers/complex_cg.py
merlinth/layers/complex_init.py
merlinth/layers/complex_maxpool.py
merlinth/layers/complex_norm.py
merlinth/layers/complex_norm_v2.py
merlinth/layers/complex_pad.py
merlinth/layers/data_consistency.py
merlinth/layers/fft.py
merlinth/layers/module.py
merlinth/layers/mri.py
merlinth/layers/warp.py
merlinth/layers/convolutional/__init__.py
merlinth/layers/convolutional/complex_conv.py
merlinth/layers/convolutional/complex_padconv.py
merlinth/layers/convolutional/padconv.py
merlinth/losses/__init__.py
merlinth/losses/hfen.py
merlinth/losses/loss_template.py
merlinth/losses/loss_utils.py
merlinth/losses/modified_vgg.py
merlinth/losses/pairwise_loss.py
merlinth/losses/ssim.py
merlinth/losses/vgg_loss.py
merlinth/models/__init__.py
merlinth/models/cnn.py
merlinth/models/foe.py
merlinth/models/tdv.py
merlinth/models/unet.py
merlinth/models/unet_complex_reg_2dt.py
merlinth/models/unet_complex_residual_block.py
merlinth/models/unet_residual.py
merlinth/optim/BlockAdam.py
merlinth/optim/__init__.py
merlinth/optim/radam.py
merlinth/test/__init__.py
merlinth/test/test_layers_complex_act.py
merlinth/test/test_layers_complex_avgpool.py
merlinth/test/test_layers_complex_maxpool.py
merlinth/test/test_layers_complex_norm.py
merlinth/test/test_layers_convolutional.py
merlinth/test/test_layers_data_consistency.py
merlinth/test/test_layers_fft.py
merlinth/test/test_layers_mri.py
merlinth/test/test_layers_warp.py
merlinth/test/test_losses.py
merlinth/test/test_models_cnn.py
merlinth/test/test_models_foe.py
merlinth/test/test_models_tdv.py
merlinth/test/test_models_unet_complex_reg_2dt.py
merlinth/test/test_models_unet_complex_residual_block.py
merlinth/test/test_models_unet_residual.py
merlinth_mri-0.4.1.dist-info/METADATA
merlinth_mri-0.4.1.dist-info/WHEEL
merlinth_mri-0.4.1.dist-info/top_level.txt
merlinth_mri-0.4.1.dist-info/RECORD
