Metadata-Version: 2.1
Name: merlinth-mri
Version: 0.4.1
Summary: Machine Enhanced Reconstruction Learning and Interpretation Networks (MERLIN) - merlinth
Home-page: https://github.com/midas-tum/merlin
Author: Kerstin Hammernik, Thomas Kuestner
Author-email: merlin.midastum@gmail.com
License: MIT
Classifier: Programming Language :: Python :: 3 :: Only
Classifier: License :: OSI Approved :: MIT License
Classifier: Operating System :: OS Independent
Classifier: Topic :: Scientific/Engineering :: Artificial Intelligence
Classifier: Topic :: Scientific/Engineering :: Medical Science Apps.
Requires-Dist: numpy >=1.15
Requires-Dist: torch >=1.0.0
Requires-Dist: torchvision >=0.2.1
